lingtreemaps/__init__.py
lingtreemaps/cli.py
lingtreemaps/helpers.py
lingtreemaps/data/MajorRivers.dbf
lingtreemaps/data/MajorRivers.prj
lingtreemaps/data/MajorRivers.sbn
lingtreemaps/data/MajorRivers.sbx
lingtreemaps/data/MajorRivers.shp
lingtreemaps/data/MajorRivers.shp.xml
lingtreemaps/data/MajorRivers.shx
lingtreemaps/data/default_config.yaml
lingtreemaps/data/world-administrative-boundaries.dbf
lingtreemaps/data/world-administrative-boundaries.prj
lingtreemaps/data/world-administrative-boundaries.shp
lingtreemaps/data/world-administrative-boundaries.shx
lingtreemaps-0.0.5.dist-info/LICENSE
lingtreemaps-0.0.5.dist-info/METADATA
lingtreemaps-0.0.5.dist-info/WHEEL
lingtreemaps-0.0.5.dist-info/entry_points.txt
lingtreemaps-0.0.5.dist-info/top_level.txt
lingtreemaps-0.0.5.dist-info/RECORD
